LICENSE
README.md
pyproject.toml
nonebot_plugin_oi_helper/__init__.py
nonebot_plugin_oi_helper/api.py
nonebot_plugin_oi_helper/command.py
nonebot_plugin_oi_helper/config.py
nonebot_plugin_oi_helper/leetcode_api.py
nonebot_plugin_oi_helper/query_api.py
nonebot_plugin_oi_helper/scheduler.py
nonebot_plugin_oi_helper/utils.py
nonebot_plugin_oi_helper-2.0.0.dist-info/METADATA
nonebot_plugin_oi_helper-2.0.0.dist-info/WHEEL
nonebot_plugin_oi_helper-2.0.0.dist-info/licenses/LICENSE
nonebot_plugin_oi_helper-2.0.0.dist-info/RECORD
