Metadata-Version: 2.4
Name: nonebot-plugin-oi-helper
Version: 2.0.0
Summary: A NoneBot2 plugin for querying OI/ACM related information, including LeetCode daily question.
Project-URL: homepage, https://github.com/talentestors/nonebot-plugin-oi-helper
Project-URL: repository, https://github.com/talentestors/nonebot-plugin-oi-helper
Project-URL: documentation, https://github.com/talentestors/nonebot-plugin-oi-helper#readme
Author-email: talentestors <talentestors@outlook.com>
License: LGPL-3.0-or-later
License-File: LICENSE
Keywords: ACM,LeetCode,OI,nonebot,plugin
Classifier: Development Status :: 4 - Beta
Classifier: Framework :: AsyncIO
Classifier: Intended Audience :: Developers
Classifier: License :: OSI Approved :: GNU Lesser General Public License v3 or later (LGPLv3+)
Classifier: Programming Language :: Python :: 3
Classifier: Programming Language :: Python :: 3.12
Classifier: Programming Language :: Python :: 3.13
Classifier: Programming Language :: Python :: 3.14
Classifier: Topic :: Software Development :: Libraries
Classifier: Topic :: Software Development :: Libraries :: Python Modules
Requires-Python: <4.0,>=3.12
Requires-Dist: httpx[brotli,http2,zstd]>=0.28.1
Requires-Dist: nonebot-plugin-apscheduler>=0.5.0
Requires-Dist: nonebot-plugin-localstore>=0.7.4
Requires-Dist: nonebot2>=2.4.2
Requires-Dist: tenacity>=9.1.2
